[
  {
    "sid": null,
    "dt": null,
    "ring_number": null,
    "ringName": null,
    "class_group_id": null,
    "class_group_sequence": null,
    "class_groupxclasses_id": null,
    "group_name": null,
    "groomName": "Groom",
    "time_sort": null,
    "class_id": null,
    "class_number": null,
    "completed_trips": null,
    "class_name": null,
    "class_type": null,
    "lastGoneIn": null,
    "remaining_trips": null,
    "estimated_end_time": null,
    "estimated_go_time": null,
    "estimated_start_time": null,
    "schedule_sequencetype": null,
    "trip_id": null,
    "latestStart": {
      "error": "#ERROR!"
    },
    "latestStatus": null,
    "total_trips": null,
    "entry_id": null,
    "backNumber": null,
    "entryNumber": null,
    "entryxclasses_uuid": null,
    "ringWalk": 0,
    "barnName": null,
    "horseName": null,
    "teamName": null,
    "riderName": null,
    "latestPlacing": null,
    "lastScore": null,
    "lastPlace": null,
    "lastPosition": null,
    "time_one": null,
    "time_two": null,
    "pid": null,
    "secondsTill": {
      "specialValue": "NaN"
    },
    "time_three": null,
    "score1": null,
    "score2": null,
    "score3": null,
    "lastTime": null,
    "latestGO": "12:00 AM",
    "runningOOG": null,
    "lastOOG": null,
    "sched_display": null,
    "is_target": null,
    "is_parent": null,
    "path_tenant": null,
    "estimatedGO00": "12:00:00",
    "estimatedGO": "12:00 AM"
  },
  {
    "sid": "200000061",
    "dt": "2026-05-07",
    "ring_number": 4,
    "ringName": "Village",
    "class_group_id": 200023700,
    "class_group_sequence": 1,
    "class_groupxclasses_id": 200035403,
    "group_name": "Training Jumper (.90m) II2d",
    "groomName": "Fernando",
    "time_sort": 28800,
    "class_id": null,
    "class_number": 750,
    "completed_trips": 20,
    "class_name": "Training Jumper (.90m) II2d",
    "class_type": "Jumpers",
    "lastGoneIn": null,
    "remaining_trips": null,
    "estimated_end_time": null,
    "estimated_go_time": null,
    "estimated_start_time": "08:00:00",
    "schedule_sequencetype": "Over Fences",
    "trip_id": null,
    "latestStart": "8:00 AM",
    "latestStatus": "Completed",
    "total_trips": 20,
    "entry_id": null,
    "backNumber": null,
    "entryNumber": null,
    "entryxclasses_uuid": null,
    "ringWalk": 0,
    "barnName": "Choco",
    "horseName": "Choco",
    "teamName": null,
    "riderName": null,
    "latestPlacing": null,
    "lastScore": null,
    "lastPlace": null,
    "lastPosition": null,
    "time_one": null,
    "time_two": null,
    "pid": 8778,
    "secondsTill": -23900,
    "time_three": null,
    "score1": null,
    "score2": null,
    "score3": null,
    "lastTime": null,
    "latestGO": "8:36 AM",
    "runningOOG": null,
    "lastOOG": 12,
    "sched_display": "Choco (12)",
    "is_target": null,
    "is_parent": null,
    "path_tenant": "8778",
    "estimatedGO00": "8:36:00",
    "estimatedGO": "8:36 AM"
  },
  {
    "sid": "200000061",
    "dt": "2026-05-07",
    "ring_number": 1,
    "ringName": "Derby",
    "class_group_id": 200023690,
    "class_group_sequence": 1,
    "class_groupxclasses_id": 200035393,
    "group_name": "1.30m Open Jumper II2.1 & 1.30m Young Jumper II2.1",
    "groomName": "Fernando",
    "time_sort": 30600,
    "class_id": null,
    "class_number": 770,
    "completed_trips": 57,
    "class_name": "1.30m Open Jumper II2.1",
    "class_type": "Jumpers",
    "lastGoneIn": null,
    "remaining_trips": null,
    "estimated_end_time": null,
    "estimated_go_time": null,
    "estimated_start_time": "08:30:00",
    "schedule_sequencetype": "Over Fences",
    "trip_id": null,
    "latestStart": "8:30 AM",
    "latestStatus": "Underway",
    "total_trips": 58,
    "entry_id": null,
    "backNumber": null,
    "entryNumber": null,
    "entryxclasses_uuid": "fallback:8778:2298:770:insider_bh",
    "ringWalk": 0,
    "barnName": "Insider",
    "horseName": "Insider",
    "teamName": null,
    "riderName": null,
    "latestPlacing": null,
    "lastScore": null,
    "lastPlace": null,
    "lastPosition": null,
    "time_one": null,
    "time_two": null,
    "pid": 8778,
    "secondsTill": -22100,
    "time_three": null,
    "score1": null,
    "score2": null,
    "score3": null,
    "lastTime": null,
    "latestGO": "9:15 AM",
    "runningOOG": 0,
    "lastOOG": 15,
    "sched_display": "Insider (15)",
    "is_target": true,
    "is_parent": null,
    "path_tenant": "8778",
    "estimatedGO00": "9:15:00",
    "estimatedGO": "9:15 AM"
  },
  {
    "sid": "200000061",
    "dt": "2026-05-07",
    "ring_number": 1,
    "ringName": "Derby",
    "class_group_id": 200023690,
    "class_group_sequence": 1,
    "class_groupxclasses_id": 200035393,
    "group_name": "1.30m Open Jumper II2.1 & 1.30m Young Jumper II2.1",
    "groomName": "Dayani",
    "time_sort": 30600,
    "class_id": null,
    "class_number": 770,
    "completed_trips": 57,
    "class_name": "1.30m Open Jumper II2.1",
    "class_type": "Jumpers",
    "lastGoneIn": null,
    "remaining_trips": null,
    "estimated_end_time": null,
    "estimated_go_time": null,
    "estimated_start_time": "08:30:00",
    "schedule_sequencetype": "Over Fences",
    "trip_id": null,
    "latestStart": "8:30 AM",
    "latestStatus": "Underway",
    "total_trips": 58,
    "entry_id": null,
    "backNumber": null,
    "entryNumber": null,
    "entryxclasses_uuid": "fallback:8778:2556:770:kindly",
    "ringWalk": 0,
    "barnName": "Bee",
    "horseName": "Bee",
    "teamName": null,
    "riderName": null,
    "latestPlacing": null,
    "lastScore": null,
    "lastPlace": null,
    "lastPosition": null,
    "time_one": null,
    "time_two": null,
    "pid": 8778,
    "secondsTill": -22100,
    "time_three": null,
    "score1": null,
    "score2": null,
    "score3": null,
    "lastTime": null,
    "latestGO": "10:09 AM",
    "runningOOG": 0,
    "lastOOG": 33,
    "sched_display": "Bee (33)",
    "is_target": true,
    "is_parent": null,
    "path_tenant": "8778",
    "estimatedGO00": "10:09:00",
    "estimatedGO": "10:09 AM"
  },
  {
    "sid": "200000061",
    "dt": "2026-05-07",
    "ring_number": 1,
    "ringName": "Derby",
    "class_group_id": 200023690,
    "class_group_sequence": 1,
    "class_groupxclasses_id": 200035393,
    "group_name": "1.30m Open Jumper II2.1 & 1.30m Young Jumper II2.1",
    "groomName": "Jackie",
    "time_sort": 30600,
    "class_id": null,
    "class_number": 770,
    "completed_trips": 57,
    "class_name": "1.30m Open Jumper II2.1",
    "class_type": "Jumpers",
    "lastGoneIn": null,
    "remaining_trips": null,
    "estimated_end_time": null,
    "estimated_go_time": null,
    "estimated_start_time": "08:30:00",
    "schedule_sequencetype": "Over Fences",
    "trip_id": null,
    "latestStart": "8:30 AM",
    "latestStatus": "Underway",
    "total_trips": 58,
    "entry_id": null,
    "backNumber": null,
    "entryNumber": null,
    "entryxclasses_uuid": "fallback:8778:2317:770:hermes_darmanville",
    "ringWalk": 0,
    "barnName": "Hermes",
    "horseName": "Hermes",
    "teamName": null,
    "riderName": null,
    "latestPlacing": null,
    "lastScore": null,
    "lastPlace": null,
    "lastPosition": null,
    "time_one": null,
    "time_two": null,
    "pid": 8778,
    "secondsTill": -22100,
    "time_three": null,
    "score1": null,
    "score2": null,
    "score3": null,
    "lastTime": null,
    "latestGO": "8:39 AM",
    "runningOOG": 0,
    "lastOOG": 3,
    "sched_display": "Hermes (3)",
    "is_target": true,
    "is_parent": null,
    "path_tenant": "8778",
    "estimatedGO00": "8:39:00",
    "estimatedGO": "8:39 AM"
  },
  {
    "sid": "200000061",
    "dt": "2026-05-07",
    "ring_number": 1,
    "ringName": "Derby",
    "class_group_id": 200023690,
    "class_group_sequence": 1,
    "class_groupxclasses_id": 200035393,
    "group_name": "1.30m Open Jumper II2.1 & 1.30m Young Jumper II2.1",
    "groomName": "Groom",
    "time_sort": 30600,
    "class_id": null,
    "class_number": 770,
    "completed_trips": 57,
    "class_name": "1.30m Open Jumper II2.1",
    "class_type": "Jumpers",
    "lastGoneIn": null,
    "remaining_trips": null,
    "estimated_end_time": null,
    "estimated_go_time": null,
    "estimated_start_time": "08:30:00",
    "schedule_sequencetype": "Over Fences",
    "trip_id": null,
    "latestStart": "8:30 AM",
    "latestStatus": "Underway",
    "total_trips": 58,
    "entry_id": null,
    "backNumber": null,
    "entryNumber": null,
    "entryxclasses_uuid": "fallback:8778:2468:770:sandenal",
    "ringWalk": 0,
    "barnName": "Sandenal",
    "horseName": "Sandenal",
    "teamName": null,
    "riderName": null,
    "latestPlacing": null,
    "lastScore": null,
    "lastPlace": null,
    "lastPosition": null,
    "time_one": null,
    "time_two": null,
    "pid": 8778,
    "secondsTill": -22100,
    "time_three": null,
    "score1": null,
    "score2": null,
    "score3": null,
    "lastTime": null,
    "latestGO": "9:12 AM",
    "runningOOG": 0,
    "lastOOG": 14,
    "sched_display": "Sandenal (14)",
    "is_target": true,
    "is_parent": null,
    "path_tenant": "8778",
    "estimatedGO00": "9:12:00",
    "estimatedGO": "9:12 AM"
  },
  {
    "sid": "200000061",
    "dt": "2026-05-07",
    "ring_number": 3,
    "ringName": "Covered",
    "class_group_id": 200023694,
    "class_group_sequence": 1,
    "class_groupxclasses_id": 200035397,
    "group_name": "1.10m Open Jumper II2d",
    "groomName": "Groom",
    "time_sort": 32400,
    "class_id": null,
    "class_number": 715,
    "completed_trips": 28,
    "class_name": "1.10m Open Jumper II2d",
    "class_type": "Jumpers",
    "lastGoneIn": null,
    "remaining_trips": null,
    "estimated_end_time": null,
    "estimated_go_time": null,
    "estimated_start_time": "09:00:00",
    "schedule_sequencetype": "Over Fences",
    "trip_id": null,
    "latestStart": "9:00 AM",
    "latestStatus": "Underway",
    "total_trips": 30,
    "entry_id": null,
    "backNumber": null,
    "entryNumber": null,
    "entryxclasses_uuid": "fallback:8778:3160:715:markanto_a",
    "ringWalk": 0,
    "barnName": "Markanto",
    "horseName": "Markanto",
    "teamName": null,
    "riderName": null,
    "latestPlacing": null,
    "lastScore": null,
    "lastPlace": null,
    "lastPosition": null,
    "time_one": null,
    "time_two": null,
    "pid": 8778,
    "secondsTill": -20300,
    "time_three": null,
    "score1": null,
    "score2": null,
    "score3": null,
    "lastTime": null,
    "latestGO": "10:30 AM",
    "runningOOG": 2,
    "lastOOG": 30,
    "sched_display": "Markanto (30)",
    "is_target": true,
    "is_parent": null,
    "path_tenant": "8778",
    "estimatedGO00": "10:30:00",
    "estimatedGO": "10:30 AM"
  },
  {
    "sid": "200000061",
    "dt": "2026-05-07",
    "ring_number": 3,
    "ringName": "Covered",
    "class_group_id": 200023694,
    "class_group_sequence": 1,
    "class_groupxclasses_id": 200035397,
    "group_name": "1.10m Open Jumper II2d",
    "groomName": "Fernando",
    "time_sort": 32400,
    "class_id": null,
    "class_number": 715,
    "completed_trips": 28,
    "class_name": "1.10m Open Jumper II2d",
    "class_type": "Jumpers",
    "lastGoneIn": null,
    "remaining_trips": null,
    "estimated_end_time": null,
    "estimated_go_time": null,
    "estimated_start_time": "09:00:00",
    "schedule_sequencetype": "Over Fences",
    "trip_id": null,
    "latestStart": "9:00 AM",
    "latestStatus": "Underway",
    "total_trips": 30,
    "entry_id": null,
    "backNumber": null,
    "entryNumber": null,
    "entryxclasses_uuid": "fallback:8778:2296:715:fernhill_kudos",
    "ringWalk": 0,
    "barnName": "Kudos",
    "horseName": "Kudos",
    "teamName": null,
    "riderName": null,
    "latestPlacing": null,
    "lastScore": null,
    "lastPlace": null,
    "lastPosition": null,
    "time_one": null,
    "time_two": null,
    "pid": 8778,
    "secondsTill": -20300,
    "time_three": null,
    "score1": null,
    "score2": null,
    "score3": null,
    "lastTime": null,
    "latestGO": "10:33 AM",
    "runningOOG": 3,
    "lastOOG": 31,
    "sched_display": "Kudos (31)",
    "is_target": true,
    "is_parent": null,
    "path_tenant": "8778",
    "estimatedGO00": "10:33:00",
    "estimatedGO": "10:33 AM"
  },
  {
    "sid": "200000061",
    "dt": "2026-05-07",
    "ring_number": 4,
    "ringName": "Village",
    "class_group_id": 200023702,
    "class_group_sequence": 3,
    "class_groupxclasses_id": 200035405,
    "group_name": "Training Jumper (1.0m) II2d & Take2 TB Jumper (1,0m) II2d",
    "groomName": "Groom",
    "time_sort": 34200,
    "class_id": null,
    "class_number": 780,
    "completed_trips": 25,
    "class_name": "Training Jumper (1.0m) II2d",
    "class_type": "Jumpers",
    "lastGoneIn": null,
    "remaining_trips": null,
    "estimated_end_time": null,
    "estimated_go_time": null,
    "estimated_start_time": "09:30:00",
    "schedule_sequencetype": "Over Fences",
    "trip_id": null,
    "latestStart": "9:30 AM",
    "latestStatus": "Underway",
    "total_trips": 28,
    "entry_id": null,
    "backNumber": null,
    "entryNumber": null,
    "entryxclasses_uuid": "fallback:8778:2802:780:calypso",
    "ringWalk": 0,
    "barnName": "Calypso",
    "horseName": "Calypso",
    "teamName": null,
    "riderName": null,
    "latestPlacing": null,
    "lastScore": null,
    "lastPlace": null,
    "lastPosition": null,
    "time_one": null,
    "time_two": null,
    "pid": 8778,
    "secondsTill": -18500,
    "time_three": null,
    "score1": null,
    "score2": null,
    "score3": null,
    "lastTime": null,
    "latestGO": "10:27 AM",
    "runningOOG": 0,
    "lastOOG": 19,
    "sched_display": "Calypso (19)",
    "is_target": true,
    "is_parent": null,
    "path_tenant": "8778",
    "estimatedGO00": "10:27:00",
    "estimatedGO": "10:27 AM"
  },
  {
    "sid": "200000061",
    "dt": "2026-05-07",
    "ring_number": 4,
    "ringName": "Village",
    "class_group_id": 200023702,
    "class_group_sequence": 3,
    "class_groupxclasses_id": 200035405,
    "group_name": "Training Jumper (1.0m) II2d & Take2 TB Jumper (1,0m) II2d",
    "groomName": "Groom",
    "time_sort": 34200,
    "class_id": null,
    "class_number": 780,
    "completed_trips": 25,
    "class_name": "Training Jumper (1.0m) II2d",
    "class_type": "Jumpers",
    "lastGoneIn": null,
    "remaining_trips": null,
    "estimated_end_time": null,
    "estimated_go_time": null,
    "estimated_start_time": "09:30:00",
    "schedule_sequencetype": "Over Fences",
    "trip_id": null,
    "latestStart": "9:30 AM",
    "latestStatus": "Underway",
    "total_trips": 28,
    "entry_id": null,
    "backNumber": null,
    "entryNumber": null,
    "entryxclasses_uuid": "fallback:8778:2817:780:mastermind",
    "ringWalk": 0,
    "barnName": "Munster",
    "horseName": "Munster",
    "teamName": null,
    "riderName": null,
    "latestPlacing": null,
    "lastScore": null,
    "lastPlace": null,
    "lastPosition": null,
    "time_one": null,
    "time_two": null,
    "pid": 8778,
    "secondsTill": -18500,
    "time_three": null,
    "score1": null,
    "score2": null,
    "score3": null,
    "lastTime": null,
    "latestGO": "10:06 AM",
    "runningOOG": 0,
    "lastOOG": 12,
    "sched_display": "Munster (12)",
    "is_target": true,
    "is_parent": null,
    "path_tenant": "8778",
    "estimatedGO00": "10:06:00",
    "estimatedGO": "10:06 AM"
  },
  {
    "sid": "200000061",
    "dt": "2026-05-07",
    "ring_number": 4,
    "ringName": "Village",
    "class_group_id": 200023702,
    "class_group_sequence": 3,
    "class_groupxclasses_id": 200035405,
    "group_name": "Training Jumper (1.0m) II2d & Take2 TB Jumper (1,0m) II2d",
    "groomName": "Fernando",
    "time_sort": 34200,
    "class_id": null,
    "class_number": 780,
    "completed_trips": 25,
    "class_name": "Training Jumper (1.0m) II2d",
    "class_type": "Jumpers",
    "lastGoneIn": null,
    "remaining_trips": null,
    "estimated_end_time": null,
    "estimated_go_time": null,
    "estimated_start_time": "09:30:00",
    "schedule_sequencetype": "Over Fences",
    "trip_id": null,
    "latestStart": "9:30 AM",
    "latestStatus": "Underway",
    "total_trips": 28,
    "entry_id": null,
    "backNumber": null,
    "entryNumber": null,
    "entryxclasses_uuid": null,
    "ringWalk": 0,
    "barnName": "Choco",
    "horseName": "Choco",
    "teamName": null,
    "riderName": null,
    "latestPlacing": null,
    "lastScore": null,
    "lastPlace": null,
    "lastPosition": null,
    "time_one": null,
    "time_two": null,
    "pid": 8778,
    "secondsTill": -18500,
    "time_three": null,
    "score1": null,
    "score2": null,
    "score3": null,
    "lastTime": null,
    "latestGO": "10:00 AM",
    "runningOOG": 0,
    "lastOOG": 10,
    "sched_display": "Choco (10)",
    "is_target": null,
    "is_parent": null,
    "path_tenant": "8778",
    "estimatedGO00": "10:00:00",
    "estimatedGO": "10:00 AM"
  },
  {
    "sid": "200000061",
    "dt": "2026-05-07",
    "ring_number": 4,
    "ringName": "Village",
    "class_group_id": 200023702,
    "class_group_sequence": 3,
    "class_groupxclasses_id": 200035405,
    "group_name": "Training Jumper (1.0m) II2d & Take2 TB Jumper (1,0m) II2d",
    "groomName": "Groom",
    "time_sort": 34200,
    "class_id": null,
    "class_number": 780,
    "completed_trips": 25,
    "class_name": "Training Jumper (1.0m) II2d",
    "class_type": "Jumpers",
    "lastGoneIn": null,
    "remaining_trips": null,
    "estimated_end_time": null,
    "estimated_go_time": null,
    "estimated_start_time": "09:30:00",
    "schedule_sequencetype": "Over Fences",
    "trip_id": null,
    "latestStart": "9:30 AM",
    "latestStatus": "Underway",
    "total_trips": 28,
    "entry_id": null,
    "backNumber": null,
    "entryNumber": null,
    "entryxclasses_uuid": null,
    "ringWalk": 0,
    "barnName": "Fento",
    "horseName": "Fento",
    "teamName": null,
    "riderName": null,
    "latestPlacing": null,
    "lastScore": null,
    "lastPlace": null,
    "lastPosition": null,
    "time_one": null,
    "time_two": null,
    "pid": 8778,
    "secondsTill": -18500,
    "time_three": null,
    "score1": null,
    "score2": null,
    "score3": null,
    "lastTime": null,
    "latestGO": "10:03 AM",
    "runningOOG": 0,
    "lastOOG": 11,
    "sched_display": "Fento (11)",
    "is_target": null,
    "is_parent": null,
    "path_tenant": "8778",
    "estimatedGO00": "10:03:00",
    "estimatedGO": "10:03 AM"
  },
  {
    "sid": "200000061",
    "dt": "2026-05-07",
    "ring_number": 3,
    "ringName": "Covered",
    "class_group_id": 200023697,
    "class_group_sequence": 4,
    "class_groupxclasses_id": 200035400,
    "group_name": "1.20m Open Jumper II2d",
    "groomName": "Dayani",
    "time_sort": 42300,
    "class_id": null,
    "class_number": 787,
    "completed_trips": 0,
    "class_name": "1.20m Open Jumper II2d",
    "class_type": "Jumpers",
    "lastGoneIn": null,
    "remaining_trips": null,
    "estimated_end_time": null,
    "estimated_go_time": null,
    "estimated_start_time": "11:45:00",
    "schedule_sequencetype": "Over Fences",
    "trip_id": null,
    "latestStart": "11:45 AM",
    "latestStatus": "Upcoming",
    "total_trips": 12,
    "entry_id": null,
    "backNumber": null,
    "entryNumber": null,
    "entryxclasses_uuid": "fallback:8778:2805:787:ideal",
    "ringWalk": 0,
    "barnName": "Doug",
    "horseName": "Doug",
    "teamName": null,
    "riderName": null,
    "latestPlacing": null,
    "lastScore": null,
    "lastPlace": null,
    "lastPosition": null,
    "time_one": null,
    "time_two": null,
    "pid": 8778,
    "secondsTill": -10400,
    "time_three": null,
    "score1": null,
    "score2": null,
    "score3": null,
    "lastTime": null,
    "latestGO": "12:18 PM",
    "runningOOG": null,
    "lastOOG": 11,
    "sched_display": "Doug (11)",
    "is_target": true,
    "is_parent": null,
    "path_tenant": "8778",
    "estimatedGO00": "12:18:00",
    "estimatedGO": "12:18 PM"
  }
]
