[
  {
    "sid": "200000056",
    "dt": "2026-03-29",
    "ring_number": 5,
    "class_group_id": 200021911,
    "class_id": 200022521,
    "completed_trips": 0,
    "class_name": "$10,000 NAL/WIHS Masters Jumper Classic Rd1 (1.15m Amateur)",
    "class_type": "Jumpers",
    "lastGoneIn": null,
    "estimated_go_time": "10:21:00",
    "estimated_start_time": "10:00:00",
    "latestStatus": "Upcoming",
    "entry_id": 200141530,
    "entryxclasses_uuid": "2BB2E1E09F3D4D228E63E9BA148C80E1",
    "secondsTill": 11704,
    "latestGO": "10:24 AM",
    "lastOOG": 8,
    "is_target": true,
    "is_parent": null,
    "path_tenant": "8778"
  },
  {
    "sid": "200000056",
    "dt": "2026-03-29",
    "ring_number": 2,
    "class_group_id": 200021893,
    "class_id": 200022594,
    "completed_trips": 0,
    "class_name": "$100 Adult Amateur Hunter 55 & Over (Sec B) U/S",
    "class_type": "Hunters",
    "lastGoneIn": null,
    "estimated_go_time": "09:45:00",
    "estimated_start_time": "10:00:00",
    "latestStatus": "Not Started",
    "entry_id": 200167904,
    "entryxclasses_uuid": "A4B6A77FD6BB4E2580BFEE11FA8079A0",
    "secondsTill": 11704,
    "latestGO": "10:00 AM",
    "lastOOG": null,
    "is_target": true,
    "is_parent": null,
    "path_tenant": "40362"
  },
  {
    "sid": "200000056",
    "dt": "2026-03-29",
    "ring_number": 12,
    "class_group_id": 200021940,
    "class_id": 200022667,
    "completed_trips": 0,
    "class_name": "$100 Medium Pony Hunter U/S CALI @ 30+",
    "class_type": "Hunters",
    "lastGoneIn": null,
    "estimated_go_time": "07:30:00",
    "estimated_start_time": "10:00:00",
    "latestStatus": "Not Started",
    "entry_id": 200225381,
    "entryxclasses_uuid": "B24DF25BBB5742C1ABFA7C50A95F5515",
    "secondsTill": 11704,
    "latestGO": "10:00 AM",
    "lastOOG": null,
    "is_target": true,
    "is_parent": null,
    "path_tenant": "8778"
  },
  {
    "sid": "200000056",
    "dt": "2026-03-29",
    "ring_number": 10,
    "class_group_id": 200021929,
    "class_id": 200022304,
    "completed_trips": 0,
    "class_name": "$1,595 1.05m Junior Jumper Classic II2b CALI @ 50+",
    "class_type": "Jumpers",
    "lastGoneIn": null,
    "estimated_go_time": "09:19:00",
    "estimated_start_time": "10:00:00",
    "latestStatus": "Upcoming",
    "entry_id": 200214666,
    "entryxclasses_uuid": "8929F0AF507F465889B7C8BC2237088B",
    "secondsTill": 11704,
    "latestGO": "12:24 PM",
    "lastOOG": 48,
    "is_target": true,
    "is_parent": null,
    "path_tenant": "8778"
  },
  {
    "sid": "200000056",
    "dt": "2026-03-29",
    "ring_number": 3,
    "class_group_id": 200021901,
    "class_id": 200022575,
    "completed_trips": 0,
    "class_name": "Low Adult Hunter (Sec. B) U/S CALI @ 30+",
    "class_type": "Hunters",
    "lastGoneIn": null,
    "estimated_go_time": "09:45:00",
    "estimated_start_time": "10:00:00",
    "latestStatus": "Not Started",
    "entry_id": 200167710,
    "entryxclasses_uuid": "902FE8F2B50A46BDBDE7C02D66DC9FB1",
    "secondsTill": 11704,
    "latestGO": "10:00 AM",
    "lastOOG": null,
    "is_target": true,
    "is_parent": null,
    "path_tenant": "40362"
  },
  {
    "sid": "200000056",
    "dt": "2026-03-29",
    "ring_number": 2,
    "class_group_id": 200021893,
    "class_id": 200022594,
    "completed_trips": 0,
    "class_name": "$100 Adult Amateur Hunter 55 & Over (Sec B) U/S",
    "class_type": "Hunters",
    "lastGoneIn": null,
    "estimated_go_time": "09:45:00",
    "estimated_start_time": "10:00:00",
    "latestStatus": "Not Started",
    "entry_id": 200167748,
    "entryxclasses_uuid": "0D9223282A524AA698D911EF8C944155",
    "secondsTill": 11704,
    "latestGO": "10:00 AM",
    "lastOOG": null,
    "is_target": true,
    "is_parent": null,
    "path_tenant": "40362"
  },
  {
    "sid": "200000056",
    "dt": "2026-03-29",
    "ring_number": 12,
    "class_group_id": 200021940,
    "class_id": 200022667,
    "completed_trips": 0,
    "class_name": "$100 Medium Pony Hunter U/S CALI @ 30+",
    "class_type": "Hunters",
    "lastGoneIn": null,
    "estimated_go_time": "07:30:00",
    "estimated_start_time": "10:00:00",
    "latestStatus": "Not Started",
    "entry_id": 200149660,
    "entryxclasses_uuid": "2C97EA84B8D34E80B0041B7CDC3DCD89",
    "secondsTill": 11704,
    "latestGO": "10:00 AM",
    "lastOOG": null,
    "is_target": true,
    "is_parent": null,
    "path_tenant": "8778"
  },
  {
    "sid": "200000056",
    "dt": "2026-03-29",
    "ring_number": 9,
    "class_group_id": 200024245,
    "class_id": 200022324,
    "completed_trips": 0,
    "class_name": "ASPCA Maclay (Section A)",
    "class_type": "Equitation",
    "lastGoneIn": null,
    "estimated_go_time": "07:53:00",
    "estimated_start_time": "10:00:00",
    "latestStatus": "Upcoming",
    "entry_id": 200149892,
    "entryxclasses_uuid": "ECE31550098B4F77BD01C719FD40CC72",
    "secondsTill": 11704,
    "latestGO": "10:15 AM",
    "lastOOG": 5,
    "is_target": true,
    "is_parent": null,
    "path_tenant": "8778"
  },
  {
    "sid": "200000056",
    "dt": "2026-03-29",
    "ring_number": 5,
    "class_group_id": 200021911,
    "class_id": 200022521,
    "completed_trips": 0,
    "class_name": "$10,000 NAL/WIHS Masters Jumper Classic Rd1 (1.15m Amateur)",
    "class_type": "Jumpers",
    "lastGoneIn": null,
    "estimated_go_time": "10:45:00",
    "estimated_start_time": "10:00:00",
    "latestStatus": "Upcoming",
    "entry_id": 200167807,
    "entryxclasses_uuid": "574D2356B42945DFB14D4E933CD653B8",
    "secondsTill": 11704,
    "latestGO": "10:48 AM",
    "lastOOG": 16,
    "is_target": true,
    "is_parent": null,
    "path_tenant": "40362"
  },
  {
    "sid": "200000056",
    "dt": "2026-03-29",
    "ring_number": 7,
    "class_group_id": 200021919,
    "class_id": 200022403,
    "completed_trips": 0,
    "class_name": "$2,500 Modified Adult Amateur Jumper II2b",
    "class_type": "Jumpers",
    "lastGoneIn": null,
    "estimated_go_time": "08:55:00",
    "estimated_start_time": "10:00:00",
    "latestStatus": "Upcoming",
    "entry_id": 200157472,
    "entryxclasses_uuid": "84F122A918CD414FA7CE41EB189A162A",
    "secondsTill": 11704,
    "latestGO": "11:27 AM",
    "lastOOG": 29,
    "is_target": true,
    "is_parent": null,
    "path_tenant": "34933"
  },
  {
    "sid": "200000056",
    "dt": "2026-03-29",
    "ring_number": 3,
    "class_group_id": 200021901,
    "class_id": 200022575,
    "completed_trips": 0,
    "class_name": "Low Adult Hunter (Sec. B) U/S CALI @ 30+",
    "class_type": "Hunters",
    "lastGoneIn": null,
    "estimated_go_time": "09:45:00",
    "estimated_start_time": "10:00:00",
    "latestStatus": "Not Started",
    "entry_id": 200167974,
    "entryxclasses_uuid": "D2EC4D30C27746A299825E4775C056A8",
    "secondsTill": 11704,
    "latestGO": "10:00 AM",
    "lastOOG": null,
    "is_target": true,
    "is_parent": null,
    "path_tenant": "40362"
  },
  {
    "sid": "200000056",
    "dt": "2026-03-29",
    "ring_number": 5,
    "class_group_id": 200021911,
    "class_id": 200022521,
    "completed_trips": 0,
    "class_name": "$10,000 NAL/WIHS Masters Jumper Classic Rd1 (1.15m Amateur)",
    "class_type": "Jumpers",
    "lastGoneIn": null,
    "estimated_go_time": "10:06:00",
    "estimated_start_time": "10:00:00",
    "latestStatus": "Upcoming",
    "entry_id": 200167952,
    "entryxclasses_uuid": "54E1B6F9D16D47488A2CC0E21986A8B9",
    "secondsTill": 11704,
    "latestGO": "10:09 AM",
    "lastOOG": 3,
    "is_target": true,
    "is_parent": null,
    "path_tenant": "40362"
  },
  {
    "sid": "200000056",
    "dt": "2026-03-29",
    "ring_number": 5,
    "class_group_id": 200021911,
    "class_id": 200022521,
    "completed_trips": 0,
    "class_name": "$10,000 NAL/WIHS Masters Jumper Classic Rd1 (1.15m Amateur)",
    "class_type": "Jumpers",
    "lastGoneIn": null,
    "estimated_go_time": "10:24:00",
    "estimated_start_time": "10:00:00",
    "latestStatus": "Upcoming",
    "entry_id": 200168039,
    "entryxclasses_uuid": "84907A071ABE4E8F9209954F09E40B37",
    "secondsTill": 11704,
    "latestGO": "10:27 AM",
    "lastOOG": 9,
    "is_target": true,
    "is_parent": null,
    "path_tenant": "40362"
  },
  {
    "sid": "200000056",
    "dt": "2026-03-29",
    "ring_number": 4,
    "class_group_id": 200021909,
    "class_id": 200022425,
    "completed_trips": 0,
    "class_name": "$15,000 NAL 1.25m Amateur Jumper Classic II2b CALI @ 80+",
    "class_type": "Jumpers",
    "lastGoneIn": null,
    "estimated_go_time": "10:06:00",
    "estimated_start_time": "10:00:00",
    "latestStatus": "Upcoming",
    "entry_id": 200223718,
    "entryxclasses_uuid": "FDEAF90C85E94F51AA43A4A36FF3A287",
    "secondsTill": 11704,
    "latestGO": "10:21 AM",
    "lastOOG": 7,
    "is_target": true,
    "is_parent": null,
    "path_tenant": "40362"
  },
  {
    "sid": "200000056",
    "dt": "2026-03-29",
    "ring_number": 2,
    "class_group_id": 200021894,
    "class_id": 200022747,
    "completed_trips": 0,
    "class_name": "$100 Adult Amateur Hunter 55 & Over (Sec B)",
    "class_type": "Hunters",
    "lastGoneIn": null,
    "estimated_go_time": "08:29:00",
    "estimated_start_time": "10:15:00",
    "latestStatus": "Upcoming",
    "entry_id": 200167748,
    "entryxclasses_uuid": "0596622970F74B8388CBD95240803302",
    "secondsTill": 12604,
    "latestGO": "11:42 AM",
    "lastOOG": 29,
    "is_target": true,
    "is_parent": true,
    "path_tenant": "40362"
  },
  {
    "sid": "200000056",
    "dt": "2026-03-29",
    "ring_number": 6,
    "class_group_id": 200021915,
    "class_id": 200022441,
    "completed_trips": 0,
    "class_name": "Low Children's Hunter CALI @ 30+",
    "class_type": "Hunters",
    "lastGoneIn": null,
    "estimated_go_time": "07:54:00",
    "estimated_start_time": "10:15:00",
    "latestStatus": "Upcoming",
    "entry_id": 200144372,
    "entryxclasses_uuid": "F592A8502AB84B1F91E615BCA639B43B",
    "secondsTill": 12604,
    "latestGO": "10:45 AM",
    "lastOOG": 10,
    "is_target": null,
    "is_parent": null,
    "path_tenant": "8778"
  },
  {
    "sid": "200000056",
    "dt": "2026-03-29",
    "ring_number": 12,
    "class_group_id": 200021941,
    "class_id": 200022496,
    "completed_trips": 0,
    "class_name": "$500 Medium Pony Conformation  Hunter CALI @ 30+",
    "class_type": "Hunters",
    "lastGoneIn": null,
    "estimated_go_time": "09:35:00",
    "estimated_start_time": "10:15:00",
    "latestStatus": "Upcoming",
    "entry_id": 200225381,
    "entryxclasses_uuid": "6AABF7BA722840AB8951730C8B71E7A3",
    "secondsTill": 12604,
    "latestGO": "12:18 PM",
    "lastOOG": 41,
    "is_target": true,
    "is_parent": true,
    "path_tenant": "8778"
  },
  {
    "sid": "200000056",
    "dt": "2026-03-29",
    "ring_number": 12,
    "class_group_id": 200021941,
    "class_id": 200022605,
    "completed_trips": 0,
    "class_name": "$500 Medium Pony Hunter Classic",
    "class_type": "Hunters",
    "lastGoneIn": null,
    "estimated_go_time": "09:45:00",
    "estimated_start_time": "10:15:00",
    "latestStatus": "Upcoming",
    "entry_id": 200149660,
    "entryxclasses_uuid": "88FD6A4417144335A96BE66FAC597B32",
    "secondsTill": 12604,
    "latestGO": "12:27 PM",
    "lastOOG": 44,
    "is_target": true,
    "is_parent": null,
    "path_tenant": "8778"
  },
  {
    "sid": "200000056",
    "dt": "2026-03-29",
    "ring_number": 12,
    "class_group_id": 200021941,
    "class_id": 200022496,
    "completed_trips": 0,
    "class_name": "$500 Medium Pony Conformation  Hunter CALI @ 30+",
    "class_type": "Hunters",
    "lastGoneIn": null,
    "estimated_go_time": "09:41:00",
    "estimated_start_time": "10:15:00",
    "latestStatus": "Upcoming",
    "entry_id": 200149660,
    "entryxclasses_uuid": "09A0EDBD046A4DDB9EB8367B7FD270AE",
    "secondsTill": 12604,
    "latestGO": "12:27 PM",
    "lastOOG": 44,
    "is_target": true,
    "is_parent": true,
    "path_tenant": "8778"
  },
  {
    "sid": "200000056",
    "dt": "2026-03-29",
    "ring_number": 12,
    "class_group_id": 200021941,
    "class_id": 200022668,
    "completed_trips": 0,
    "class_name": "$630 Medium Pony  Hunter Handy CALI @ 30+",
    "class_type": "Hunters",
    "lastGoneIn": null,
    "estimated_go_time": "09:37:00",
    "estimated_start_time": "10:15:00",
    "latestStatus": "Upcoming",
    "entry_id": 200225381,
    "entryxclasses_uuid": "BC2AB88790084645A5059FDFEFAD9D0B",
    "secondsTill": 12604,
    "latestGO": "12:21 PM",
    "lastOOG": 42,
    "is_target": null,
    "is_parent": null,
    "path_tenant": "8778"
  },
  {
    "sid": "200000056",
    "dt": "2026-03-29",
    "ring_number": 2,
    "class_group_id": 200021894,
    "class_id": 200022412,
    "completed_trips": 0,
    "class_name": "$100 Adult Amateur Hunter 55 & Over (Sec B)",
    "class_type": "Hunters",
    "lastGoneIn": null,
    "estimated_go_time": "08:28:00",
    "estimated_start_time": "10:15:00",
    "latestStatus": "Upcoming",
    "entry_id": 200167748,
    "entryxclasses_uuid": "309462063888462592655812DF281842",
    "secondsTill": 12604,
    "latestGO": "11:42 AM",
    "lastOOG": 29,
    "is_target": null,
    "is_parent": null,
    "path_tenant": "40362"
  },
  {
    "sid": "200000056",
    "dt": "2026-03-29",
    "ring_number": 3,
    "class_group_id": 200021902,
    "class_id": 200022760,
    "completed_trips": 0,
    "class_name": "Low Adult Hunter (Sec. B) CALI @ 30+",
    "class_type": "Hunters",
    "lastGoneIn": null,
    "estimated_go_time": "09:25:30",
    "estimated_start_time": "10:15:00",
    "latestStatus": "Upcoming",
    "entry_id": 200167710,
    "entryxclasses_uuid": "244E5D8A3FFC4B00948B43F161F361E7",
    "secondsTill": 12604,
    "latestGO": "12:09 PM",
    "lastOOG": 38,
    "is_target": null,
    "is_parent": null,
    "path_tenant": "40362"
  },
  {
    "sid": "200000056",
    "dt": "2026-03-29",
    "ring_number": 12,
    "class_group_id": 200021941,
    "class_id": 200022605,
    "completed_trips": 0,
    "class_name": "$500 Medium Pony Hunter Classic",
    "class_type": "Hunters",
    "lastGoneIn": null,
    "estimated_go_time": "09:39:00",
    "estimated_start_time": "10:15:00",
    "latestStatus": "Upcoming",
    "entry_id": 200225381,
    "entryxclasses_uuid": "058E6444AA0A490098BD742ACDBAB012",
    "secondsTill": 12604,
    "latestGO": "12:18 PM",
    "lastOOG": 41,
    "is_target": true,
    "is_parent": null,
    "path_tenant": "8778"
  },
  {
    "sid": "200000056",
    "dt": "2026-03-29",
    "ring_number": 12,
    "class_group_id": 200021941,
    "class_id": 200022668,
    "completed_trips": 0,
    "class_name": "$630 Medium Pony  Hunter Handy CALI @ 30+",
    "class_type": "Hunters",
    "lastGoneIn": null,
    "estimated_go_time": "09:43:00",
    "estimated_start_time": "10:15:00",
    "latestStatus": "Upcoming",
    "entry_id": 200149660,
    "entryxclasses_uuid": "5B0CA1DBA31A49CBB4DD4D696BB30B35",
    "secondsTill": 12604,
    "latestGO": "12:30 PM",
    "lastOOG": 45,
    "is_target": null,
    "is_parent": null,
    "path_tenant": "8778"
  },
  {
    "sid": "200000056",
    "dt": "2026-03-29",
    "ring_number": 3,
    "class_group_id": 200021902,
    "class_id": 200022372,
    "completed_trips": 0,
    "class_name": "Low Adult Hunter (Sec. B) CALI @ 30+",
    "class_type": "Hunters",
    "lastGoneIn": null,
    "estimated_go_time": "09:23:15",
    "estimated_start_time": "10:15:00",
    "latestStatus": "Upcoming",
    "entry_id": 200167710,
    "entryxclasses_uuid": "C1C4258899AB447BA56E4CF3443D7709",
    "secondsTill": 12604,
    "latestGO": "12:12 PM",
    "lastOOG": 39,
    "is_target": true,
    "is_parent": true,
    "path_tenant": "40362"
  },
  {
    "sid": "200000056",
    "dt": "2026-03-29",
    "ring_number": 6,
    "class_group_id": 200021915,
    "class_id": 200022461,
    "completed_trips": 0,
    "class_name": "Low Children's Hunter CALI @ 30+",
    "class_type": "Hunters",
    "lastGoneIn": null,
    "estimated_go_time": "07:53:00",
    "estimated_start_time": "10:15:00",
    "latestStatus": "Upcoming",
    "entry_id": 200144372,
    "entryxclasses_uuid": "818B177E6CE64915A44153719BDCF0F7",
    "secondsTill": 12604,
    "latestGO": "10:42 AM",
    "lastOOG": 9,
    "is_target": true,
    "is_parent": true,
    "path_tenant": "8778"
  },
  {
    "sid": "200000056",
    "dt": "2026-03-29",
    "ring_number": 3,
    "class_group_id": 200021902,
    "class_id": 200022372,
    "completed_trips": 0,
    "class_name": "Low Adult Hunter (Sec. B) CALI @ 30+",
    "class_type": "Hunters",
    "lastGoneIn": null,
    "estimated_go_time": "09:59:15",
    "estimated_start_time": "10:15:00",
    "latestStatus": "Upcoming",
    "entry_id": 200167974,
    "entryxclasses_uuid": "E1603187F97747A08CC0620615CE1778",
    "secondsTill": 12604,
    "latestGO": "1:00 PM",
    "lastOOG": 55,
    "is_target": true,
    "is_parent": true,
    "path_tenant": "40362"
  },
  {
    "sid": "200000056",
    "dt": "2026-03-29",
    "ring_number": 2,
    "class_group_id": 200021894,
    "class_id": 200022412,
    "completed_trips": 0,
    "class_name": "$100 Adult Amateur Hunter 55 & Over (Sec B)",
    "class_type": "Hunters",
    "lastGoneIn": null,
    "estimated_go_time": "08:26:00",
    "estimated_start_time": "10:15:00",
    "latestStatus": "Upcoming",
    "entry_id": 200167904,
    "entryxclasses_uuid": "3B4A1FC6E897449AB4B6FE3E5B3893C7",
    "secondsTill": 12604,
    "latestGO": "11:36 AM",
    "lastOOG": 27,
    "is_target": null,
    "is_parent": null,
    "path_tenant": "40362"
  },
  {
    "sid": "200000056",
    "dt": "2026-03-29",
    "ring_number": 3,
    "class_group_id": 200021902,
    "class_id": 200022760,
    "completed_trips": 0,
    "class_name": "Low Adult Hunter (Sec. B) CALI @ 30+",
    "class_type": "Hunters",
    "lastGoneIn": null,
    "estimated_go_time": "10:01:30",
    "estimated_start_time": "10:15:00",
    "latestStatus": "Upcoming",
    "entry_id": 200167974,
    "entryxclasses_uuid": "749599D8779F4D029A684D48DEF40EF9",
    "secondsTill": 12604,
    "latestGO": "12:57 PM",
    "lastOOG": 54,
    "is_target": null,
    "is_parent": null,
    "path_tenant": "40362"
  },
  {
    "sid": "200000056",
    "dt": "2026-03-29",
    "ring_number": 2,
    "class_group_id": 200021894,
    "class_id": 200022747,
    "completed_trips": 0,
    "class_name": "$100 Adult Amateur Hunter 55 & Over (Sec B)",
    "class_type": "Hunters",
    "lastGoneIn": null,
    "estimated_go_time": "08:27:00",
    "estimated_start_time": "10:15:00",
    "latestStatus": "Upcoming",
    "entry_id": 200167904,
    "entryxclasses_uuid": "D7638D678567487082FAC4756C484332",
    "secondsTill": 12604,
    "latestGO": "11:36 AM",
    "lastOOG": 27,
    "is_target": true,
    "is_parent": true,
    "path_tenant": "40362"
  },
  {
    "sid": "200000056",
    "dt": "2026-03-29",
    "ring_number": 2,
    "class_group_id": 200021895,
    "class_id": 200022472,
    "completed_trips": 0,
    "class_name": "$100 Junior Hunter 3'3\" 16-17 U/S",
    "class_type": "Hunters",
    "lastGoneIn": null,
    "estimated_go_time": "09:00:00",
    "estimated_start_time": "10:47:00",
    "latestStatus": "Not Started",
    "entry_id": 200167672,
    "entryxclasses_uuid": "4B6391E4EBAF4B628AB92FEF32164D44",
    "secondsTill": 14524,
    "latestGO": "10:47 AM",
    "lastOOG": null,
    "is_target": true,
    "is_parent": null,
    "path_tenant": "40362"
  },
  {
    "sid": "200000056",
    "dt": "2026-03-29",
    "ring_number": 9,
    "class_group_id": 200024246,
    "class_id": 200022700,
    "completed_trips": 0,
    "class_name": "ASPCA Maclay (Section B)",
    "class_type": "Equitation",
    "lastGoneIn": null,
    "estimated_go_time": "09:38:00",
    "estimated_start_time": "10:52:00",
    "latestStatus": "Upcoming",
    "entry_id": 200151073,
    "entryxclasses_uuid": "43BD05A15EC24C489722DB2567880054",
    "secondsTill": 14824,
    "latestGO": "11:07 AM",
    "lastOOG": 5,
    "is_target": true,
    "is_parent": null,
    "path_tenant": "8778"
  },
  {
    "sid": "200000056",
    "dt": "2026-03-29",
    "ring_number": 5,
    "class_group_id": 200021959,
    "class_id": 200022352,
    "completed_trips": 0,
    "class_name": "$10,000 NAL/WIHS Masters Jumper Classic Rd2 (1.15m Amateur)",
    "class_type": "Jumpers",
    "lastGoneIn": null,
    "estimated_go_time": "08:44:00",
    "estimated_start_time": "11:00:00",
    "latestStatus": "Upcoming",
    "entry_id": 200167807,
    "entryxclasses_uuid": "EC2F1B7A09E5401895369F2120F34FBE",
    "secondsTill": 15304,
    "latestGO": "11:00 AM",
    "lastOOG": null,
    "is_target": true,
    "is_parent": null,
    "path_tenant": "40362"
  },
  {
    "sid": "200000056",
    "dt": "2026-03-29",
    "ring_number": 5,
    "class_group_id": 200021959,
    "class_id": 200022352,
    "completed_trips": 0,
    "class_name": "$10,000 NAL/WIHS Masters Jumper Classic Rd2 (1.15m Amateur)",
    "class_type": "Jumpers",
    "lastGoneIn": null,
    "estimated_go_time": "08:44:00",
    "estimated_start_time": "11:00:00",
    "latestStatus": "Upcoming",
    "entry_id": 200141530,
    "entryxclasses_uuid": "864BA91D48C340FCA9F8687AA641FEB9",
    "secondsTill": 15304,
    "latestGO": "11:00 AM",
    "lastOOG": null,
    "is_target": true,
    "is_parent": null,
    "path_tenant": "8778"
  },
  {
    "sid": "200000056",
    "dt": "2026-03-29",
    "ring_number": 5,
    "class_group_id": 200021959,
    "class_id": 200022352,
    "completed_trips": 0,
    "class_name": "$10,000 NAL/WIHS Masters Jumper Classic Rd2 (1.15m Amateur)",
    "class_type": "Jumpers",
    "lastGoneIn": null,
    "estimated_go_time": "08:44:00",
    "estimated_start_time": "11:00:00",
    "latestStatus": "Upcoming",
    "entry_id": 200167952,
    "entryxclasses_uuid": "C205D32B5ED14052A2674E1EF0F945BB",
    "secondsTill": 15304,
    "latestGO": "11:00 AM",
    "lastOOG": null,
    "is_target": true,
    "is_parent": null,
    "path_tenant": "40362"
  },
  {
    "sid": "200000056",
    "dt": "2026-03-29",
    "ring_number": 5,
    "class_group_id": 200021959,
    "class_id": 200022352,
    "completed_trips": 0,
    "class_name": "$10,000 NAL/WIHS Masters Jumper Classic Rd2 (1.15m Amateur)",
    "class_type": "Jumpers",
    "lastGoneIn": null,
    "estimated_go_time": "08:44:00",
    "estimated_start_time": "11:00:00",
    "latestStatus": "Upcoming",
    "entry_id": 200168039,
    "entryxclasses_uuid": "3F452BD91EF04B9FBB3CCECF4AB17567",
    "secondsTill": 15304,
    "latestGO": "11:00 AM",
    "lastOOG": null,
    "is_target": true,
    "is_parent": null,
    "path_tenant": "40362"
  },
  {
    "sid": "200000056",
    "dt": "2026-03-29",
    "ring_number": 2,
    "class_group_id": 200021896,
    "class_id": 200022646,
    "completed_trips": 0,
    "class_name": "$500 Junior Hunter 3'3\" 16-17",
    "class_type": "Hunters",
    "lastGoneIn": null,
    "estimated_go_time": "09:55:00",
    "estimated_start_time": "11:02:00",
    "latestStatus": "Upcoming",
    "entry_id": 200167672,
    "entryxclasses_uuid": "D055E21DA09142918C652E62A3FA8EE6",
    "secondsTill": 15424,
    "latestGO": "11:35 AM",
    "lastOOG": 11,
    "is_target": true,
    "is_parent": true,
    "path_tenant": "40362"
  },
  {
    "sid": "200000056",
    "dt": "2026-03-29",
    "ring_number": 2,
    "class_group_id": 200021896,
    "class_id": 200022432,
    "completed_trips": 0,
    "class_name": "$800 Junior Hunter 3'3\" 16-17 Stake",
    "class_type": "Hunters",
    "lastGoneIn": null,
    "estimated_go_time": "09:56:00",
    "estimated_start_time": "11:02:00",
    "latestStatus": "Upcoming",
    "entry_id": 200167672,
    "entryxclasses_uuid": "87DF2A7D616947A981B971C1469159B0",
    "secondsTill": 15424,
    "latestGO": "11:38 AM",
    "lastOOG": 12,
    "is_target": null,
    "is_parent": null,
    "path_tenant": "40362"
  },
  {
    "sid": "200000056",
    "dt": "2026-03-29",
    "ring_number": 11,
    "class_group_id": 200021938,
    "class_id": 200022892,
    "completed_trips": 0,
    "class_name": "$500 Green Pony Hunter Classic",
    "class_type": "Hunters",
    "lastGoneIn": null,
    "estimated_go_time": "00:00:00",
    "estimated_start_time": "11:13:00",
    "latestStatus": "Upcoming",
    "entry_id": 200150983,
    "entryxclasses_uuid": "CA6E5E310B4447C39DDD206BF4DBF12D",
    "secondsTill": 20704,
    "latestGO": "12:37 PM",
    "lastOOG": 28,
    "is_target": true,
    "is_parent": null,
    "path_tenant": "8778"
  },
  {
    "sid": "200000056",
    "dt": "2026-03-29",
    "ring_number": 11,
    "class_group_id": 200021936,
    "class_id": 200022365,
    "completed_trips": 0,
    "class_name": "$400 Small Green Pony Hunter",
    "class_type": "Hunters",
    "lastGoneIn": null,
    "estimated_go_time": "00:00:00",
    "estimated_start_time": "11:13:00",
    "latestStatus": "Upcoming",
    "entry_id": 200150983,
    "entryxclasses_uuid": "20704D6FB1DB41EC96BF9F8C3913BB23",
    "secondsTill": 16084,
    "latestGO": "12:07 PM",
    "lastOOG": 18,
    "is_target": true,
    "is_parent": true,
    "path_tenant": "8778"
  },
  {
    "sid": "200000056",
    "dt": "2026-03-29",
    "ring_number": 11,
    "class_group_id": 200021936,
    "class_id": 200022625,
    "completed_trips": 0,
    "class_name": "$400 Small Green Pony Hunter",
    "class_type": "Hunters",
    "lastGoneIn": null,
    "estimated_go_time": "00:00:00",
    "estimated_start_time": "11:13:00",
    "latestStatus": "Upcoming",
    "entry_id": 200150983,
    "entryxclasses_uuid": "E62D00CC054948808A7B0B62AD048330",
    "secondsTill": 16084,
    "latestGO": "12:10 PM",
    "lastOOG": 19,
    "is_target": null,
    "is_parent": null,
    "path_tenant": "8778"
  },
  {
    "sid": "200000056",
    "dt": "2026-03-29",
    "ring_number": 5,
    "class_group_id": 200021912,
    "class_id": 200022484,
    "completed_trips": 0,
    "class_name": "$15,000 NAL 1.35m Amateur Jumper Classic II2b",
    "class_type": "Jumpers",
    "lastGoneIn": null,
    "estimated_go_time": "09:52:00",
    "estimated_start_time": "11:25:00",
    "latestStatus": "Upcoming",
    "entry_id": 200149732,
    "entryxclasses_uuid": "3A12800DE8164605BE3A7DDA13DDFB14",
    "secondsTill": 16804,
    "latestGO": "11:49 AM",
    "lastOOG": 8,
    "is_target": true,
    "is_parent": null,
    "path_tenant": "8778"
  },
  {
    "sid": "200000056",
    "dt": "2026-03-29",
    "ring_number": 5,
    "class_group_id": 200021912,
    "class_id": 200022484,
    "completed_trips": 0,
    "class_name": "$15,000 NAL 1.35m Amateur Jumper Classic II2b",
    "class_type": "Jumpers",
    "lastGoneIn": null,
    "estimated_go_time": "09:53:00",
    "estimated_start_time": "11:25:00",
    "latestStatus": "Upcoming",
    "entry_id": 200154187,
    "entryxclasses_uuid": "980D8BEB9C67427BB2CA0425DB57D844",
    "secondsTill": 16804,
    "latestGO": "11:52 AM",
    "lastOOG": 9,
    "is_target": true,
    "is_parent": null,
    "path_tenant": "8778"
  },
  {
    "sid": "200000056",
    "dt": "2026-03-29",
    "ring_number": 5,
    "class_group_id": 200021912,
    "class_id": 200022484,
    "completed_trips": 0,
    "class_name": "$15,000 NAL 1.35m Amateur Jumper Classic II2b",
    "class_type": "Jumpers",
    "lastGoneIn": null,
    "estimated_go_time": "10:37:00",
    "estimated_start_time": "11:25:00",
    "latestStatus": "Upcoming",
    "entry_id": 200168028,
    "entryxclasses_uuid": "C516D7DB0CD544859CBF84612792D2A1",
    "secondsTill": 16804,
    "latestGO": "2:04 PM",
    "lastOOG": 53,
    "is_target": true,
    "is_parent": null,
    "path_tenant": "40362"
  },
  {
    "sid": "200000056",
    "dt": "2026-03-29",
    "ring_number": 4,
    "class_group_id": 200021910,
    "class_id": 200022628,
    "completed_trips": 0,
    "class_name": "$15,000 NAL 1.25m Junior Jumper Classic II2b",
    "class_type": "Jumpers",
    "lastGoneIn": null,
    "estimated_go_time": "12:00:00",
    "estimated_start_time": "11:30:00",
    "latestStatus": "Upcoming",
    "entry_id": 200149969,
    "entryxclasses_uuid": "7D4AFE7F443B418B9D43751DAEF18B54",
    "secondsTill": 17104,
    "latestGO": "12:03 PM",
    "lastOOG": 11,
    "is_target": true,
    "is_parent": null,
    "path_tenant": "8778"
  },
  {
    "sid": "200000056",
    "dt": "2026-03-29",
    "ring_number": 10,
    "class_group_id": 200021930,
    "class_id": 200022354,
    "completed_trips": 0,
    "class_name": "$1,595 1.05m Amateur Jumper Classic 36 & Over II2b",
    "class_type": "Jumpers",
    "lastGoneIn": null,
    "estimated_go_time": "10:45:00",
    "estimated_start_time": "11:38:00",
    "latestStatus": "Upcoming",
    "entry_id": 200217293,
    "entryxclasses_uuid": "84C992127BF245C08F87BBC95A5F7994",
    "secondsTill": 17704,
    "latestGO": "11:41 AM",
    "lastOOG": 1,
    "is_target": true,
    "is_parent": null,
    "path_tenant": "34933"
  },
  {
    "sid": "200000056",
    "dt": "2026-03-29",
    "ring_number": 9,
    "class_group_id": 200024247,
    "class_id": 200022549,
    "completed_trips": 0,
    "class_name": "Dover Saddlery USEF Hunter Seat Medal (Section A)",
    "class_type": "Equitation",
    "lastGoneIn": null,
    "estimated_go_time": "11:29:00",
    "estimated_start_time": "11:44:00",
    "latestStatus": "Upcoming",
    "entry_id": 200149892,
    "entryxclasses_uuid": "772A6872A2AF4F6F8B68439E66FFB8C8",
    "secondsTill": 17944,
    "latestGO": "12:08 PM",
    "lastOOG": 8,
    "is_target": true,
    "is_parent": null,
    "path_tenant": "8778"
  },
  {
    "sid": "200000056",
    "dt": "2026-03-29",
    "ring_number": 7,
    "class_group_id": 200021921,
    "class_id": 200022506,
    "completed_trips": 0,
    "class_name": "$2,500 NAL/WIHS 1.15m Junior Jumper Classic 15-17 II2b",
    "class_type": "Jumpers",
    "lastGoneIn": null,
    "estimated_go_time": "11:25:00",
    "estimated_start_time": "12:10:00",
    "latestStatus": "Upcoming",
    "entry_id": 200168086,
    "entryxclasses_uuid": "4A372275C25240BBA41DBE7EDA637C49",
    "secondsTill": 19504,
    "latestGO": "12:25 PM",
    "lastOOG": 5,
    "is_target": true,
    "is_parent": null,
    "path_tenant": "40362"
  },
  {
    "sid": "200000056",
    "dt": "2026-03-29",
    "ring_number": 10,
    "class_group_id": 200021931,
    "class_id": 200022353,
    "completed_trips": 0,
    "class_name": "$1,595 1.05m Amateur Jumper Classic 18-35 II2b",
    "class_type": "Jumpers",
    "lastGoneIn": null,
    "estimated_go_time": "12:57:00",
    "estimated_start_time": "12:28:00",
    "latestStatus": "Upcoming",
    "entry_id": 200150582,
    "entryxclasses_uuid": "14017F3DD4A24E0191D9BC4004233E46",
    "secondsTill": 20704,
    "latestGO": "1:34 PM",
    "lastOOG": 22,
    "is_target": true,
    "is_parent": null,
    "path_tenant": "8778"
  },
  {
    "sid": "200000056",
    "dt": "2026-03-29",
    "ring_number": 10,
    "class_group_id": 200021931,
    "class_id": 200022353,
    "completed_trips": 0,
    "class_name": "$1,595 1.05m Amateur Jumper Classic 18-35 II2b",
    "class_type": "Jumpers",
    "lastGoneIn": null,
    "estimated_go_time": "12:55:00",
    "estimated_start_time": "12:28:00",
    "latestStatus": "Upcoming",
    "entry_id": 200217090,
    "entryxclasses_uuid": "CFD2919EB9FE4E2ABE61A8EFDDB6DDFD",
    "secondsTill": 20704,
    "latestGO": "1:31 PM",
    "lastOOG": 21,
    "is_target": true,
    "is_parent": null,
    "path_tenant": "8778"
  },
  {
    "sid": "200000056",
    "dt": "2026-03-29",
    "ring_number": 9,
    "class_group_id": 200024248,
    "class_id": 200022754,
    "completed_trips": 0,
    "class_name": "Dover Saddlery USEF Hunter Seat Medal (Section B)",
    "class_type": "Equitation",
    "lastGoneIn": null,
    "estimated_go_time": "13:13:00",
    "estimated_start_time": "12:45:00",
    "latestStatus": "Upcoming",
    "entry_id": 200151073,
    "entryxclasses_uuid": "811C6CF725E249BD8F10A7ED462990F4",
    "secondsTill": 21604,
    "latestGO": "1:30 PM",
    "lastOOG": 15,
    "is_target": true,
    "is_parent": null,
    "path_tenant": "8778"
  },
  {
    "sid": "200000056",
    "dt": "2026-03-29",
    "ring_number": 12,
    "class_group_id": 200024244,
    "class_id": 200022632,
    "completed_trips": 0,
    "class_name": "$100 Small Pony Hunter U/S CALI @ 30+",
    "class_type": "Hunters",
    "lastGoneIn": null,
    "estimated_go_time": "11:30:00",
    "estimated_start_time": "12:55:00",
    "latestStatus": "Not Started",
    "entry_id": 200180817,
    "entryxclasses_uuid": "131C40F86E2146B2A288A47861D5ECC9",
    "secondsTill": 22204,
    "latestGO": "12:55 PM",
    "lastOOG": null,
    "is_target": true,
    "is_parent": null,
    "path_tenant": "8778"
  },
  {
    "sid": "200000056",
    "dt": "2026-03-29",
    "ring_number": 12,
    "class_group_id": 200024244,
    "class_id": 200022632,
    "completed_trips": 0,
    "class_name": "$100 Small Pony Hunter U/S CALI @ 30+",
    "class_type": "Hunters",
    "lastGoneIn": null,
    "estimated_go_time": "11:30:00",
    "estimated_start_time": "12:55:00",
    "latestStatus": "Not Started",
    "entry_id": 200155967,
    "entryxclasses_uuid": "C472B4FCB53F498AAD0BE19A9F106581",
    "secondsTill": 22204,
    "latestGO": "12:55 PM",
    "lastOOG": null,
    "is_target": true,
    "is_parent": null,
    "path_tenant": "8778"
  },
  {
    "sid": "200000056",
    "dt": "2026-03-29",
    "ring_number": 12,
    "class_group_id": 200021942,
    "class_id": 200022315,
    "completed_trips": 0,
    "class_name": "$500 Small Pony  Hunter CALI @ 30+",
    "class_type": "Hunters",
    "lastGoneIn": null,
    "estimated_go_time": "13:30:00",
    "estimated_start_time": "13:10:00",
    "latestStatus": "Upcoming",
    "entry_id": 200155967,
    "entryxclasses_uuid": "3FF301FD485E404595C9B7C7C8763AC3",
    "secondsTill": 23104,
    "latestGO": "2:43 PM",
    "lastOOG": 31,
    "is_target": true,
    "is_parent": true,
    "path_tenant": "8778"
  },
  {
    "sid": "200000056",
    "dt": "2026-03-29",
    "ring_number": 12,
    "class_group_id": 200021942,
    "class_id": 200022673,
    "completed_trips": 0,
    "class_name": "$500 Small Pony Hunter Classic",
    "class_type": "Hunters",
    "lastGoneIn": null,
    "estimated_go_time": "13:34:00",
    "estimated_start_time": "13:10:00",
    "latestStatus": "Upcoming",
    "entry_id": 200155967,
    "entryxclasses_uuid": "9754857B006C455A9D7BCEFB2FBB2D3A",
    "secondsTill": 23104,
    "latestGO": "2:43 PM",
    "lastOOG": 31,
    "is_target": true,
    "is_parent": null,
    "path_tenant": "8778"
  },
  {
    "sid": "200000056",
    "dt": "2026-03-29",
    "ring_number": 12,
    "class_group_id": 200021942,
    "class_id": 200022529,
    "completed_trips": 0,
    "class_name": "$630 Small Pony Hunter Handy CALI @ 30+",
    "class_type": "Hunters",
    "lastGoneIn": null,
    "estimated_go_time": "13:38:00",
    "estimated_start_time": "13:10:00",
    "latestStatus": "Upcoming",
    "entry_id": 200180817,
    "entryxclasses_uuid": "8AD2C36B68354A9C9EB1DB93B0CE23F1",
    "secondsTill": 23104,
    "latestGO": "2:55 PM",
    "lastOOG": 35,
    "is_target": null,
    "is_parent": null,
    "path_tenant": "8778"
  },
  {
    "sid": "200000056",
    "dt": "2026-03-29",
    "ring_number": 12,
    "class_group_id": 200021942,
    "class_id": 200022315,
    "completed_trips": 0,
    "class_name": "$500 Small Pony  Hunter CALI @ 30+",
    "class_type": "Hunters",
    "lastGoneIn": null,
    "estimated_go_time": "13:36:00",
    "estimated_start_time": "13:10:00",
    "latestStatus": "Upcoming",
    "entry_id": 200180817,
    "entryxclasses_uuid": "CD6847E7512E4067BAC477E3C97B500A",
    "secondsTill": 23104,
    "latestGO": "2:52 PM",
    "lastOOG": 34,
    "is_target": true,
    "is_parent": true,
    "path_tenant": "8778"
  },
  {
    "sid": "200000056",
    "dt": "2026-03-29",
    "ring_number": 12,
    "class_group_id": 200021942,
    "class_id": 200022673,
    "completed_trips": 0,
    "class_name": "$500 Small Pony Hunter Classic",
    "class_type": "Hunters",
    "lastGoneIn": null,
    "estimated_go_time": "13:40:00",
    "estimated_start_time": "13:10:00",
    "latestStatus": "Upcoming",
    "entry_id": 200180817,
    "entryxclasses_uuid": "84E996880AEF4D689A258E877499C606",
    "secondsTill": 23104,
    "latestGO": "2:52 PM",
    "lastOOG": 34,
    "is_target": true,
    "is_parent": null,
    "path_tenant": "8778"
  },
  {
    "sid": "200000056",
    "dt": "2026-03-29",
    "ring_number": 12,
    "class_group_id": 200021942,
    "class_id": 200022529,
    "completed_trips": 0,
    "class_name": "$630 Small Pony Hunter Handy CALI @ 30+",
    "class_type": "Hunters",
    "lastGoneIn": null,
    "estimated_go_time": "13:32:00",
    "estimated_start_time": "13:10:00",
    "latestStatus": "Upcoming",
    "entry_id": 200155967,
    "entryxclasses_uuid": "D30AD117F77E4195BEAFF9E38F53A3B2",
    "secondsTill": 23104,
    "latestGO": "2:46 PM",
    "lastOOG": 32,
    "is_target": null,
    "is_parent": null,
    "path_tenant": "8778"
  },
  {
    "sid": "200000056",
    "dt": "2026-03-29",
    "ring_number": 6,
    "class_group_id": 200021918,
    "class_id": 200022495,
    "completed_trips": 0,
    "class_name": "Children's Hunter 14 & Under CALI @ 30+",
    "class_type": "Hunters",
    "lastGoneIn": null,
    "estimated_go_time": "13:59:00",
    "estimated_start_time": "13:15:00",
    "latestStatus": "Upcoming",
    "entry_id": 200142700,
    "entryxclasses_uuid": "847F67F0A09B4C7C97773167E8CB43BD",
    "secondsTill": 23404,
    "latestGO": "3:30 PM",
    "lastOOG": 45,
    "is_target": true,
    "is_parent": true,
    "path_tenant": "8778"
  },
  {
    "sid": "200000056",
    "dt": "2026-03-29",
    "ring_number": 5,
    "class_group_id": 200021913,
    "class_id": 200022600,
    "completed_trips": 0,
    "class_name": "$15,000 NAL 1.35m Junior Jumper Classic II2b",
    "class_type": "Jumpers",
    "lastGoneIn": null,
    "estimated_go_time": "14:00:00",
    "estimated_start_time": "13:15:00",
    "latestStatus": "Upcoming",
    "entry_id": 200214039,
    "entryxclasses_uuid": "AF0991A4535A4440A18D22A948A53A8B",
    "secondsTill": 23404,
    "latestGO": "3:33 PM",
    "lastOOG": 46,
    "is_target": true,
    "is_parent": null,
    "path_tenant": "8778"
  },
  {
    "sid": "200000056",
    "dt": "2026-03-29",
    "ring_number": 6,
    "class_group_id": 200021918,
    "class_id": 200022679,
    "completed_trips": 0,
    "class_name": "Children's Hunter 14 & Under CALI @ 30+",
    "class_type": "Hunters",
    "lastGoneIn": null,
    "estimated_go_time": "14:00:00",
    "estimated_start_time": "13:15:00",
    "latestStatus": "Upcoming",
    "entry_id": 200142700,
    "entryxclasses_uuid": "29E9D990F68F400DB7FF7976434BD15D",
    "secondsTill": 23404,
    "latestGO": "3:33 PM",
    "lastOOG": 46,
    "is_target": null,
    "is_parent": null,
    "path_tenant": "8778"
  },
  {
    "sid": "200000056",
    "dt": "2026-03-29",
    "ring_number": 10,
    "class_group_id": 200021932,
    "class_id": 200022591,
    "completed_trips": 0,
    "class_name": "$2,500 NAL/WIHS 1.15m Junior Jumper Classic 14 & Under II2b",
    "class_type": "Jumpers",
    "lastGoneIn": null,
    "estimated_go_time": "14:14:00",
    "estimated_start_time": "14:00:00",
    "latestStatus": "Upcoming",
    "entry_id": 200150438,
    "entryxclasses_uuid": "5322E53A2DEB4BDD96D9FCC2E075C11C",
    "secondsTill": 26104,
    "latestGO": "2:24 PM",
    "lastOOG": 8,
    "is_target": true,
    "is_parent": null,
    "path_tenant": "8778"
  },
  {
    "sid": "200000056",
    "dt": "2026-03-29",
    "ring_number": 13,
    "class_group_id": 200021954,
    "class_id": 200022463,
    "completed_trips": 0,
    "class_name": "Rusty Stirrup Equitation Flat",
    "class_type": "Equitation",
    "lastGoneIn": null,
    "estimated_go_time": "13:40:00",
    "estimated_start_time": "14:42:30",
    "latestStatus": "Not Started",
    "entry_id": 200168062,
    "entryxclasses_uuid": "601337B6D73F47B9B848C956EF788A66",
    "secondsTill": 28654,
    "latestGO": "2:42 PM",
    "lastOOG": null,
    "is_target": true,
    "is_parent": null,
    "path_tenant": "40362"
  },
  {
    "sid": "200000056",
    "dt": "2026-03-29",
    "ring_number": 13,
    "class_group_id": 200021955,
    "class_id": 200022560,
    "completed_trips": 0,
    "class_name": "Rusty Stirrup Hunter U/S CALI @ 10+",
    "class_type": "Hunters",
    "lastGoneIn": null,
    "estimated_go_time": "13:45:00",
    "estimated_start_time": "14:52:30",
    "latestStatus": "Not Started",
    "entry_id": 200168062,
    "entryxclasses_uuid": "22EFEA49219E47CD95EBCC4DDCE9F284",
    "secondsTill": 29254,
    "latestGO": "2:52 PM",
    "lastOOG": null,
    "is_target": true,
    "is_parent": null,
    "path_tenant": "40362"
  }
]
